{
  "name": "Garatge de Prova",
  "description": "Tecnologia d'avantguarda i experiència certificada per portar la teva mobilitat al següent nivell. Manteniment, reparació i millora amb la màxima eficiència.",
  "sector": "general",
  "features": {
    "booking": false,
    "ecommerce": false,
    "blog": true,
    "gallery": false,
    "faq": false
  },
  "theme": {
    "primary": "#a855f7",
    "layout": "modern"
  },
  "landing": {
    "sections": [
      {
        "id": "hero",
        "type": "hero"
      },
      {
        "id": "about",
        "type": "about"
      },
      {
        "id": "services",
        "type": "services"
      },
      {
        "id": "cta_banner",
        "type": "cta_banner"
      },
      {
        "id": "testimonials",
        "type": "testimonials"
      },
      {
        "id": "map",
        "type": "map"
      },
      {
        "id": "contact",
        "type": "contact"
      },
      {
        "id": "faq",
        "type": "faq"
      },
      {
        "id": "featured_products",
        "type": "featured_products"
      }
    ]
  },
  "contact": {
    "email": "info@canjosep.com",
    "phone": "+34697974872",
    "address": "Jofre El Pilos 25",
    "socials": {
      "instagram": "",
      "linkedin": "",
      "twitter": ""
    }
  }
}